{
    "file_name": "0001-01BB1AE7n_1_1.png",
    "attributes": {
        "_via_img_metadata": {
            "file_attributes": {},
            "regions": [
                {
                    "id": "8d2f0c2eceb44db3b31706d82563f307",
                    "shape_attributes": {
                        "name": "rect",
                        "x": 310,
                        "y": 2717,
                        "width": 28,
                        "height": 30
                    },
                    "region_attributes": {
                        "formal_key": "",
                        "key_type": "other",
                        "label": 74,
                        "note": "",
                        "text_category": "",
                        "text_type": "",
                        "tags": []
                    }
                },
                {
                    "id": "df8574e99d404e6a8bf5058bc725bb06",
                    "shape_attributes": {
                        "name": "rect",
                        "x": 314,
                        "y": 2683,
                        "width": 140,
                        "height": 66
                    },
                    "region_attributes": {
                        "formal_key": "",
                        "key_type": "other",
                        "label": "-",
                        "note": "",
                        "text_category": "",
                        "text_type": "",
                        "tags": []
                    }
                },
                {
                    "id": "fc006473f77845c9a6d72dc84833a889",
                    "shape_attributes": {
                        "name": "rect",
                        "x": 1096,
                        "y": 2629,
                        "width": 78,
                        "height": 78
                    },
                    "region_attributes": {
                        "formal_key": "",
                        "key_type": "other",
                        "label": "\u54ab",
                        "note": "",
                        "text_category": "",
                        "text_type": "",
                        "tags": []
                    }
                },
                {
                    "id": "dbdd931a91864fb292d5bf36d745dae2",
                    "shape_attributes": {
                        "name": "rect",
                        "x": 815,
                        "y": 2636,
                        "width": 41,
                        "height": 38
                    },
                    "region_attributes": {
                        "formal_key": "",
                        "key_type": "other",
                        "label": "\u822c",
                        "note": "",
                        "text_category": "",
                        "text_type": "",
                        "tags": []
                    }
                },
                {
                    "id": "0a5d86ddab524de08cb87644b2c44433",
                    "shape_attributes": {
                        "name": "rect",
                        "x": 1062,
                        "y": 2634,
                        "width": 29,
                        "height": 29
                    },
                    "region_attributes": {
                        "formal_key": "",
                        "key_type": "other",
                        "label": "\u3044",
                        "note": "",
                        "text_category": "",
                        "text_type": "",
                        "tags": []
                    }
                },
                {
                    "id": "ee4264b1917f499eb77870d358f258eb",
                    "shape_attributes": {
                        "name": "polygon",
                        "all_points_x": [
                            1001,
                            1053,
                            1060,
                            1008
                        ],
                        "all_points_y": [
                            2619,
                            2610,
                            2644,
                            2653
                        ]
                    },
                    "region_attributes": {
                        "formal_key": "",
                        "key_type": "other",
                        "label": "\u30ad",
                        "note": "",
                        "text_category": "",
                        "text_type": "",
                        "tags": []
                    }
                },
                {
                    "id": "eba53663ef9e4d9c9d29d67e69dc3842",
                    "shape_attributes": {
                        "name": "rect",
                        "x": 802,
                        "y": 2569,
                        "width": 80,
                        "height": 67
                    },
                    "region_attributes": {
                        "formal_key": "",
                        "key_type": "other",
                        "label": "\u30b8",
                        "note": "",
                        "text_category": "",
                        "text_type": "",
                        "tags": []
                    }
                },
                {
                    "id": "1f9e15b2c1f74261ad503964483fe96a",
                    "shape_attributes": {
                        "name": "rect",
                        "x": 783,
                        "y": 2514,
                        "width": 404,
                        "height": 95
                    },
                    "region_attributes": {
                        "formal_key": "",
                        "key_type": "other",
                        "label": "2\u56de6\u56de",
                        "note": "",
                        "text_category": "",
                        "text_type": "",
                        "tags": []
                    }
                },
                {
                    "id": "d6293ddb99a24418a0c11c46cda75e8a",
                    "shape_attributes": {
                        "name": "rect",
                        "x": 584,
                        "y": 2376,
                        "width": 382,
                        "height": 45
                    },
                    "region_attributes": {
                        "formal_key": "",
                        "key_type": "other",
                        "label": "\u75db\u98a8\u3092\u8abf\u3079\u308b\u691c\u67fb\u3067\u3059\u3002",
                        "note": "",
                        "text_category": "",
                        "text_type": "",
                        "tags": []
                    }
                },
                {
                    "id": "e1e47bca805947ce85cb53dfa21311b7",
                    "shape_attributes": {
                        "name": "rect",
                        "x": 308,
                        "y": 2374,
                        "width": 92,
                        "height": 49
                    },
                    "region_attributes": {
                        "formal_key": "",
                        "key_type": "other",
                        "label": "\u5c3f\u9178",
                        "note": "",
                        "text_category": "",
                        "text_type": "",
                        "tags": []
                    }
                },
                {
                    "id": "000f0d9b86954bd5972e247c1a7ec4a1",
                    "shape_attributes": {
                        "name": "rect",
                        "x": 586,
                        "y": 2307,
                        "width": 1309,
                        "height": 62
                    },
                    "region_attributes": {
                        "formal_key": "",
                        "key_type": "other",
                        "label": "\u814e\u81d3\u306e\u6a5f\u80fd\u3092\u8abf\u3079\u307e\u3059.2019\u5e74\u5ea6\u304b\u3089\u30af\u30ec\u30a2\u30c1\u30cb\u30f3\u3068eGCFR\u304c\u8ffd\u52a0\u3055\u308c\u3066\u3044\u307e\u3059.",
                        "note": "",
                        "text_category": "",
                        "text_type": "",
                        "tags": []
                    }
                },
                {
                    "id": "f9537e8179e94c12af7484c5e579ffa9",
                    "shape_attributes": {
                        "name": "rect",
                        "x": 312,
                        "y": 2305,
                        "width": 128,
                        "height": 49
                    },
                    "region_attributes": {
                        "formal_key": "",
                        "key_type": "other",
                        "label": "\u814e\u6a5f\u80fd",
                        "note": "",
                        "text_category": "",
                        "text_type": "",
                        "tags": []
                    }
                },
                {
                    "id": "0b9a33b8e7674727b73c3dab75078d78",
                    "shape_attributes": {
                        "name": "rect",
                        "x": 591,
                        "y": 2238,
                        "width": 101,
                        "height": 49
                    },
                    "region_attributes": {
                        "formal_key": "",
                        "key_type": "other",
                        "label": "\u307e\u3059,",
                        "note": "",
                        "text_category": "",
                        "text_type": "",
                        "tags": []
                    }
                },
                {
                    "id": "de61259f0e0d4a91a55d311469dcadb7",
                    "shape_attributes": {
                        "name": "rect",
                        "x": 595,
                        "y": 2173,
                        "width": 1305,
                        "height": 65
                    },
                    "region_attributes": {
                        "formal_key": "",
                        "key_type": "other",
                        "label": "\u7cd6\u5c3f\u75c5\u306e\u5371\u967a\u5ea6\u3092\u8abf\u3079\u307e\u3059.HbA1c~\u6700\u8fd11-2\u304b\u6708\u306e\u8840\u7cd6\u306e\u72b6\u614b\u3092\u77e5\u308b\u3053\u3068\u304c\u3067\u304d",
                        "note": "",
                        "text_category": "",
                        "text_type": "",
                        "tags": []
                    }
                },
                {
                    "id": "a467fecc99224edf9b649c33a4708a29",
                    "shape_attributes": {
                        "name": "rect",
                        "x": 319,
                        "y": 2171,
                        "width": 135,
                        "height": 47
                    },
                    "region_attributes": {
                        "formal_key": "",
                        "key_type": "other",
                        "label": "\u7cd6\u4ee3\u8b1d",
                        "note": "",
                        "text_category": "",
                        "text_type": "",
                        "tags": []
                    }
                },
                {
                    "id": "77abd2238f8d477e8e111afa4e4817e6",
                    "shape_attributes": {
                        "name": "rect",
                        "x": 598,
                        "y": 2109,
                        "width": 1221,
                        "height": 58
                    },
                    "region_attributes": {
                        "formal_key": "",
                        "key_type": "other",
                        "label": "\u52d5\u8108\u786c\u5316\u306e\u5371\u967a\u5ea6\u3092\u8abf\u3079\u307e\u3059.HDL-C\u306f\u5584\u7389\u3067\u52d5\u8108\u786c\u5316\u3092\u9632\u3050\u50cd\u304d\u3092\u3057\u307e\u3059",
                        "note": "",
                        "text_category": "",
                        "text_type": "",
                        "tags": []
                    }
                },
                {
                    "id": "9bf76fc9635a48f4b36fffad820b0401",
                    "shape_attributes": {
                        "name": "rect",
                        "x": 330,
                        "y": 2105,
                        "width": 157,
                        "height": 46
                    },
                    "region_attributes": {
                        "formal_key": "",
                        "key_type": "other",
                        "label": "\u8102\u8cea\u691c\u67fb",
                        "note": "",
                        "text_category": "",
                        "text_type": "",
                        "tags": []
                    }
                },
                {
                    "id": "4a38cb25f5f64de480bd66423437f27e",
                    "shape_attributes": {
                        "name": "rect",
                        "x": 600,
                        "y": 2045,
                        "width": 1089,
                        "height": 56
                    },
                    "region_attributes": {
                        "formal_key": "",
                        "key_type": "other",
                        "label": "\u809d\u81d3\u306e\u6a5f\u80fd\u3092\u8abf\u3079\u307e\u3059.\u30a2\u30eb\u30b3\u30fc\u30eb\u591a\u91cf,\u8102\u80aa\u809d\u306a\u3069\u3067\u4e0a\u6607\u3057\u307e\u3059.",
                        "note": "",
                        "text_category": "",
                        "text_type": "",
                        "tags": []
                    }
                },
                {
                    "id": "14b8ac417f484597af2348cd5b67ccac",
                    "shape_attributes": {
                        "name": "rect",
                        "x": 332,
                        "y": 2040,
                        "width": 126,
                        "height": 47
                    },
                    "region_attributes": {
                        "formal_key": "",
                        "key_type": "other",
                        "label": "\u809d\u6a5f\u80fd",
                        "note": "",
                        "text_category": "",
                        "text_type": "",
                        "tags": []
                    }
                },
                {
                    "id": "362749c338c64b8ea4f3749861687cf0",
                    "shape_attributes": {
                        "name": "rect",
                        "x": 602,
                        "y": 1982,
                        "width": 930,
                        "height": 54
                    },
                    "region_attributes": {
                        "formal_key": "",
                        "key_type": "other",
                        "label": "\u8d64\u8840\u7403,\u8840\u8272\u7d20,\u30d8\u30de\u30c8\u30af\u30ea\u30c3\u30c8~\u8ca7\u8840\u3092\u8abf\u3079\u308b\u691c\u67fb\u3067\u3059.",
                        "note": "",
                        "text_category": "",
                        "text_type": "",
                        "tags": []
                    }
                },
                {
                    "id": "4c5ee26edd6f44a4a7768c086d9b6984",
                    "shape_attributes": {
                        "name": "rect",
                        "x": 202,
                        "y": 1969,
                        "width": 38,
                        "height": 16
                    },
                    "region_attributes": {
                        "formal_key": "",
                        "key_type": "other",
                        "label": ":,.",
                        "note": "",
                        "text_category": "",
                        "text_type": "",
                        "tags": []
                    }
                },
                {
                    "id": "51bf6aaca6bd4f58844c3b512ea078c4",
                    "shape_attributes": {
                        "name": "rect",
                        "x": 604,
                        "y": 1925,
                        "width": 1031,
                        "height": 53
                    },
                    "region_attributes": {
                        "formal_key": "",
                        "key_type": "other",
                        "label": "\u767d\u8840\u7403\u3078\u591a\u3044\u3068\u4f53\u306e\u4e2d\u3067\u708e\u75c7\u53cd\u5fdc\u304c\u8d77\u304d\u3066\u3044\u308b\u53ef\u80fd\u6027\u304c\u3042\u308a\u307e\u3059",
                        "note": "",
                        "text_category": "",
                        "text_type": "",
                        "tags": []
                    }
                },
                {
                    "id": "107d3922c64d4163aeac50f4f46a40e0",
                    "shape_attributes": {
                        "name": "rect",
                        "x": 341,
                        "y": 1923,
                        "width": 151,
                        "height": 37
                    },
                    "region_attributes": {
                        "formal_key": "",
                        "key_type": "other",
                        "label": "\u8840\u6db2\u4e00\u822c",
                        "note": "",
                        "text_category": "",
                        "text_type": "",
                        "tags": []
                    }
                },
                {
                    "id": "27b094fa32a2483e899b86981e0ba2c4",
                    "shape_attributes": {
                        "name": "rect",
                        "x": 128,
                        "y": 1920,
                        "width": 155,
                        "height": 40
                    },
                    "region_attributes": {
                        "formal_key": "",
                        "key_type": "other",
                        "label": "\u8840\u6db2\u691c\u67fb",
                        "note": "",
                        "text_category": "",
                        "text_type": "",
                        "tags": []
                    }
                },
                {
                    "id": "e9cca375a6384e159e8ca2e16a125473",
                    "shape_attributes": {
                        "name": "rect",
                        "x": 602,
                        "y": 1865,
                        "width": 375,
                        "height": 42
                    },
                    "region_attributes": {
                        "formal_key": "",
                        "key_type": "other",
                        "label": "\u5fc3\u81d3\u306e\u6a5f\u80fd\u3092\u8abf\u3079\u307e\u3059\u3002",
                        "note": "",
                        "text_category": "",
                        "text_type": "",
                        "tags": []
                    }
                },
                {
                    "id": "d8d15207440d40a980ec5e1f8e015a72",
                    "shape_attributes": {
                        "name": "rect",
                        "x": 118,
                        "y": 1859,
                        "width": 125,
                        "height": 41
                    },
                    "region_attributes": {
                        "formal_key": "",
                        "key_type": "other",
                        "label": "\u5fc3\u96fb\u56f3",
                        "note": "",
                        "text_category": "",
                        "text_type": "",
                        "tags": []
                    }
                },
                {
                    "id": "fb69570d5bd04d9db67840fd6315dfa2",
                    "shape_attributes": {
                        "name": "rect",
                        "x": 602,
                        "y": 1804,
                        "width": 227,
                        "height": 41
                    },
                    "region_attributes": {
                        "formal_key": "",
                        "key_type": "other",
                        "label": "\u529b\u3092\u8abf\u3079\u307e\u3059\u3002",
                        "note": "",
                        "text_category": "",
                        "text_type": "",
                        "tags": []
                    }
                },
                {
                    "id": "8157d7c5289e498bba858f6b78bc6a1c",
                    "shape_attributes": {
                        "name": "rect",
                        "x": 600,
                        "y": 1745,
                        "width": 1284,
                        "height": 58
                    },
                    "region_attributes": {
                        "formal_key": "",
                        "key_type": "other",
                        "label": "\u5fc3\u81d3\u306e\u30dd\u30f3\u30d7\u4f5c\u7528\u306b\u3088\u3063\u3066\u8840\u6db2\u304c\u5168\u8eab\u306b\u9001\u308a\u51fa\u3055\u308c\u308b\u3068\u304d\u3001\u8840\u7ba1\u306b\u4e0e\u3048\u3089\u308c\u308b\u5727",
                        "note": "",
                        "text_category": "",
                        "text_type": "",
                        "tags": []
                    }
                },
                {
                    "id": "0a210232e96b44c8b7aa0d6fa91e086e",
                    "shape_attributes": {
                        "name": "rect",
                        "x": 115,
                        "y": 1740,
                        "width": 87,
                        "height": 42
                    },
                    "region_attributes": {
                        "formal_key": "",
                        "key_type": "other",
                        "label": "\u8840\u5727",
                        "note": "",
                        "text_category": "",
                        "text_type": "",
                        "tags": []
                    }
                },
                {
                    "id": "dc2ad4b47b554cb58221af027ed7a496",
                    "shape_attributes": {
                        "name": "rect",
                        "x": 598,
                        "y": 1682,
                        "width": 655,
                        "height": 50
                    },
                    "region_attributes": {
                        "formal_key": "",
                        "key_type": "other",
                        "label": "\u80ba,\u5fc3\u81d3.\u5927\u52d5\u8108\u306e\u72b6\u614b\u3092\u8abf\u3079\u3066\u3044\u307e\u3059.",
                        "note": "",
                        "text_category": "",
                        "text_type": "",
                        "tags": []
                    }
                },
                {
                    "id": "87349be89f17442497487168d4823756",
                    "shape_attributes": {
                        "name": "rect",
                        "x": 112,
                        "y": 1678,
                        "width": 162,
                        "height": 38
                    },
                    "region_attributes": {
                        "formal_key": "",
                        "key_type": "other",
                        "label": "\u80f8\u90e8X\u7dda",
                        "note": "",
                        "text_category": "",
                        "text_type": "",
                        "tags": []
                    }
                },
                {
                    "id": "08e31432173145bd9b03f03d90779378",
                    "shape_attributes": {
                        "name": "rect",
                        "x": 598,
                        "y": 1620,
                        "width": 985,
                        "height": 54
                    },
                    "region_attributes": {
                        "formal_key": "",
                        "key_type": "other",
                        "label": "\u57fa\u6e96\u5024(-)\u3092\u8d85\u3048\u305f\u5834\u5408.\u7cd6\u5c3f\u75c5\u3084\u814e\u81d3\u306e\u969c\u5bb3\u304c\u7591\u308f\u308c\u307e\u3059.",
                        "note": "",
                        "text_category": "",
                        "text_type": "",
                        "tags": []
                    }
                },
                {
                    "id": "05164c40b0744823ab254340dde0a24c",
                    "shape_attributes": {
                        "name": "rect",
                        "x": 330,
                        "y": 1618,
                        "width": 225,
                        "height": 38
                    },
                    "region_attributes": {
                        "formal_key": "",
                        "key_type": "other",
                        "label": "\u7cd6\u00b7\u86cb\u767d\u30fb\u6c88\u6d41",
                        "note": "",
                        "text_category": "",
                        "text_type": "",
                        "tags": []
                    }
                },
                {
                    "id": "1a77f4bd40a2496cb227509321888d1e",
                    "shape_attributes": {
                        "name": "rect",
                        "x": 108,
                        "y": 1614,
                        "width": 130,
                        "height": 46
                    },
                    "region_attributes": {
                        "formal_key": "",
                        "key_type": "other",
                        "label": "\u5c3f\u691c\u67fb",
                        "note": "",
                        "text_category": "",
                        "text_type": "",
                        "tags": []
                    }
                },
                {
                    "id": "e345932753904ec99da9df72bf3ac27a",
                    "shape_attributes": {
                        "name": "rect",
                        "x": 600,
                        "y": 1560,
                        "width": 1102,
                        "height": 54
                    },
                    "region_attributes": {
                        "formal_key": "",
                        "key_type": "other",
                        "label": "\u7c73\u4f1a\u8a71\u6cd5\u3078\u8a3a\u5bdf\u306e\u969b\u306b\u533b\u5e2b\u3068\u306e\u4f1a\u8a71\u306e\u3084\u308a\u53d6\u308a\u306e\u4e2d\u3067\u691c\u67fb\u3057\u3066\u3044\u307e\u3059",
                        "note": "",
                        "text_category": "",
                        "text_type": "",
                        "tags": []
                    }
                },
                {
                    "id": "708bf99324804897a92feac2dd4f38b5",
                    "shape_attributes": {
                        "name": "rect",
                        "x": 598,
                        "y": 1498,
                        "width": 298,
                        "height": 45
                    },
                    "region_attributes": {
                        "formal_key": "",
                        "key_type": "other",
                        "label": "\u3053\u3068\u3092\u610f\u5473\u3057\u307e\u3059,",
                        "note": "",
                        "text_category": "",
                        "text_type": "",
                        "tags": []
                    }
                },
                {
                    "id": "36753637e73b4cc6bb2a6d94d22e0a00",
                    "shape_attributes": {
                        "name": "rect",
                        "x": 329,
                        "y": 1486,
                        "width": 154,
                        "height": 55
                    },
                    "region_attributes": {
                        "formal_key": "",
                        "key_type": "other",
                        "label": "*\u4f1a\u8a71\u6cd5",
                        "note": "",
                        "text_category": "",
                        "text_type": "",
                        "tags": []
                    }
                },
                {
                    "id": "4799827b344f480ea2ed5fc3de112682",
                    "shape_attributes": {
                        "name": "rect",
                        "x": 593,
                        "y": 1433,
                        "width": 1237,
                        "height": 65
                    },
                    "region_attributes": {
                        "formal_key": "",
                        "key_type": "other",
                        "label": "\u5c0f\u3055\u306a\u97f3\u306e\u5f37\u3055(dB)\u3092\u8abf\u3079\u307e\u3059.\u6570\u5024\u304c\u5927\u304d\u304f\u306a\u308b\u307b\u3069\u8074\u529b\u304c\u4f4e\u4e0b\u3057\u3066\u3044\u308b",
                        "note": "",
                        "text_category": "",
                        "text_type": "",
                        "tags": []
                    }
                },
                {
                    "id": "a4063355d07f4d54a9f28b88bf88a738",
                    "shape_attributes": {
                        "name": "rect",
                        "x": 353,
                        "y": 1429,
                        "width": 200,
                        "height": 49
                    },
                    "region_attributes": {
                        "formal_key": "",
                        "key_type": "other",
                        "label": "\u30e1\u30fc\u30bf\u30fc\u6cd5",
                        "note": "",
                        "text_category": "",
                        "text_type": "",
                        "tags": []
                    }
                },
                {
                    "id": "6cb7dd9f5b5c494cac3dcd2707a752be",
                    "shape_attributes": {
                        "name": "rect",
                        "x": 596,
                        "y": 1376,
                        "width": 1221,
                        "height": 60
                    },
                    "region_attributes": {
                        "formal_key": "",
                        "key_type": "other",
                        "label": "*\u30aa\u30fc\u30b8\u30aa\u30e1\u30fc\u30bf\u30fc\u6cd5~1000HZ(\u4f4e\u97f3\u57df)/4000HZ(\u9ad8\u97f3\u57df)\u3067\u805e\u3053\u3048\u308b\u4e00\u756a",
                        "note": "",
                        "text_category": "",
                        "text_type": "",
                        "tags": []
                    }
                },
                {
                    "id": "32aa20a84a134cce8c4eef17b536074a",
                    "shape_attributes": {
                        "name": "rect",
                        "x": 326,
                        "y": 1366,
                        "width": 195,
                        "height": 50
                    },
                    "region_attributes": {
                        "formal_key": "",
                        "key_type": "other",
                        "label": "\u30ad\u30aa\u30fc\u30b8\u30aa",
                        "note": "",
                        "text_category": "",
                        "text_type": "",
                        "tags": []
                    }
                },
                {
                    "id": "1a26c3dd79ee4b609809b82d397fa7d2",
                    "shape_attributes": {
                        "name": "rect",
                        "x": 103,
                        "y": 1367,
                        "width": 83,
                        "height": 44
                    },
                    "region_attributes": {
                        "formal_key": "",
                        "key_type": "other",
                        "label": "\u8074\u529b",
                        "note": "",
                        "text_category": "",
                        "text_type": "",
                        "tags": []
                    }
                },
                {
                    "id": "7d3a23b70fe44e2e8a5e3d1632f4899f",
                    "shape_attributes": {
                        "name": "rect",
                        "x": 589,
                        "y": 1316,
                        "width": 801,
                        "height": 51
                    },
                    "region_attributes": {
                        "formal_key": "",
                        "key_type": "other",
                        "label": "\u773c\u93e1\u3084\u30b3\u30f3\u30bf\u30af\u30c8\u306f\u77ef\u6b63\u8996\u529b\u3067\u8a18\u8f09\u3055\u308c\u3066\u3044\u307e\u3059",
                        "note": "",
                        "text_category": "",
                        "text_type": "",
                        "tags": []
                    }
                },
                {
                    "id": "cdba9b064a8a43c9b31305e1b564b408",
                    "shape_attributes": {
                        "name": "rect",
                        "x": 99,
                        "y": 1305,
                        "width": 85,
                        "height": 42
                    },
                    "region_attributes": {
                        "formal_key": "",
                        "key_type": "other",
                        "label": "\u8996\u529b",
                        "note": "",
                        "text_category": "",
                        "text_type": "",
                        "tags": []
                    }
                },
                {
                    "id": "8da619049b124bd79e922abea50176d4",
                    "shape_attributes": {
                        "name": "rect",
                        "x": 587,
                        "y": 1253,
                        "width": 451,
                        "height": 47
                    },
                    "region_attributes": {
                        "formal_key": "",
                        "key_type": "other",
                        "label": "\u5185\u81d3\u8102\u80aa\u306e\u84c4\u7a4d\u3092\u8abf\u3079\u307e\u3059\u3002",
                        "note": "",
                        "text_category": "",
                        "text_type": "",
                        "tags": []
                    }
                },
                {
                    "id": "4a3159edc0644707ac2d53b79598f6bf",
                    "shape_attributes": {
                        "name": "rect",
                        "x": 317,
                        "y": 1245,
                        "width": 83,
                        "height": 44
                    },
                    "region_attributes": {
                        "formal_key": "",
                        "key_type": "other",
                        "label": "\u8179\u56f2",
                        "note": "",
                        "text_category": "",
                        "text_type": "",
                        "tags": []
                    }
                },
                {
                    "id": "67f2f492b80341b4bab02daa5a2421b3",
                    "shape_attributes": {
                        "name": "rect",
                        "x": 582,
                        "y": 1189,
                        "width": 862,
                        "height": 58
                    },
                    "region_attributes": {
                        "formal_key": "",
                        "key_type": "other",
                        "label": "BMI22\u304c\u6700\u3082\u75be\u60a3\u306b\u306a\u308b\u78ba\u7387\u304c\u4f4e\u3044\u3068\u8a00\u308f\u308c\u3066\u3044\u307e\u3059\u3002",
                        "note": "",
                        "text_category": "",
                        "text_type": "",
                        "tags": []
                    }
                },
                {
                    "id": "dd55bd6c2df2427fa3d50f7936d3a51d",
                    "shape_attributes": {
                        "name": "rect",
                        "x": 312,
                        "y": 1180,
                        "width": 70,
                        "height": 45
                    },
                    "region_attributes": {
                        "formal_key": "",
                        "key_type": "other",
                        "label": "BMI",
                        "note": "",
                        "text_category": "",
                        "text_type": "",
                        "tags": []
                    }
                },
                {
                    "id": "009f0140890d44559ea371f190fe0090",
                    "shape_attributes": {
                        "name": "rect",
                        "x": 584,
                        "y": 1129,
                        "width": 526,
                        "height": 49
                    },
                    "region_attributes": {
                        "formal_key": "",
                        "key_type": "other",
                        "label": "\u80a5\u6e80\u3084\u3084\u305b\u3067\u306a\u3044\u304b\u3092\u8abf\u3079\u307e\u3059.",
                        "note": "",
                        "text_category": "",
                        "text_type": "",
                        "tags": []
                    }
                },
                {
                    "id": "61b703bfb2f749bcb1c85cb10cc6733a",
                    "shape_attributes": {
                        "name": "rect",
                        "x": 311,
                        "y": 1118,
                        "width": 239,
                        "height": 49
                    },
                    "region_attributes": {
                        "formal_key": "",
                        "key_type": "other",
                        "label": "\u8eab\u9577\u00b7\u4f53\u91cd\u00b7",
                        "note": "",
                        "text_category": "",
                        "text_type": "",
                        "tags": []
                    }
                },
                {
                    "id": "588256462678461e91bf9675716327ab",
                    "shape_attributes": {
                        "name": "rect",
                        "x": 91,
                        "y": 1113,
                        "width": 159,
                        "height": 45
                    },
                    "region_attributes": {
                        "formal_key": "",
                        "key_type": "other",
                        "label": "\u8eab\u4f53\u6e2c\u5b9a",
                        "note": "",
                        "text_category": "",
                        "text_type": "",
                        "tags": []
                    }
                },
                {
                    "id": "cfabd764ddbb4f7fa4d88ffc6526f28b",
                    "shape_attributes": {
                        "name": "rect",
                        "x": 311,
                        "y": 1020,
                        "width": 487,
                        "height": 63
                    },
                    "region_attributes": {
                        "formal_key": "",
                        "key_type": "other",
                        "label": "\u5065\u5eb7\u8a3a\u65ad\u306e\u9805\u76ee\u306e\u8aac\u660e",
                        "note": "",
                        "text_category": "",
                        "text_type": "",
                        "tags": []
                    }
                },
                {
                    "id": "d12fddb6800246629ed22728573d39be",
                    "shape_attributes": {
                        "name": "rect",
                        "x": 719,
                        "y": 920,
                        "width": 1055,
                        "height": 65
                    },
                    "region_attributes": {
                        "formal_key": "",
                        "key_type": "other",
                        "label": "\u53d7\u8a3a\u306e\u969b\u306f\u3001\u3053\u306e\u7528\u7d19\u3068\u540c\u5c01\u306e\u4f9d\u983c\u66f8\u304c\u3042\u308c\u3070\u6301\u53c2\u3057\u3066\u304f\u3060\u3055\u3044\u3002",
                        "note": "",
                        "text_category": "",
                        "text_type": "",
                        "tags": []
                    }
                },
                {
                    "id": "181d24f9d55541c0ae05bd59830e8598",
                    "shape_attributes": {
                        "name": "rect",
                        "x": 138,
                        "y": 869,
                        "width": 417,
                        "height": 58
                    },
                    "region_attributes": {
                        "formal_key": "",
                        "key_type": "other",
                        "label": "D2:\u8981\u7cbe\u67fbD1:\u8981\u6cbb\u7642",
                        "note": "",
                        "text_category": "",
                        "text_type": "",
                        "tags": []
                    }
                },
                {
                    "id": "08625906813046308d612f180de548ae",
                    "shape_attributes": {
                        "name": "rect",
                        "x": 771,
                        "y": 860,
                        "width": 947,
                        "height": 60
                    },
                    "region_attributes": {
                        "formal_key": "",
                        "key_type": "other",
                        "label": "\u304d\u3061\u3093\u3068\u75c5\u9662\u3092\u53d7\u8a3a\u3057\u3066\u3001\u5c02\u9580\u533b\u306e\u6307\u793a\u306b\u5f93\u3063\u3066\u304f\u3060\u3055\u3044.",
                        "note": "",
                        "text_category": "",
                        "text_type": "",
                        "tags": []
                    }
                },
                {
                    "id": "f4ec6871dda8469e87f9785c93ee17f0",
                    "shape_attributes": {
                        "name": "rect",
                        "x": 908,
                        "y": 780,
                        "width": 855,
                        "height": 63
                    },
                    "region_attributes": {
                        "formal_key": "",
                        "key_type": "other",
                        "label": "\u6cbb\u7642\u3057\u3066\u3044\u308b\u75c5\u6c17\u3092\u304d\u3061\u3093\u3068\u7ba1\u7406\u3057\u3066\u3044\u304d\u307e\u3057\u3087\u3046.",
                        "note": "",
                        "text_category": "",
                        "text_type": "",
                        "tags": []
                    }
                },
                {
                    "id": "f60e5838af8a44eeb3fb425c40bc6a5b",
                    "shape_attributes": {
                        "name": "rect",
                        "x": 401,
                        "y": 766,
                        "width": 305,
                        "height": 57
                    },
                    "region_attributes": {
                        "formal_key": "",
                        "key_type": "other",
                        "label": "F:\u5224\u5b9a\u4e0d\u80fd\u00b7\u672a\u691c",
                        "note": "",
                        "text_category": "",
                        "text_type": "",
                        "tags": []
                    }
                },
                {
                    "id": "67b7d8aa3a744f6c80db62a063bdc020",
                    "shape_attributes": {
                        "name": "rect",
                        "x": 107,
                        "y": 755,
                        "width": 158,
                        "height": 52
                    },
                    "region_attributes": {
                        "formal_key": "",
                        "key_type": "other",
                        "label": "E:\u6cbb\u7642\u4e2d",
                        "note": "",
                        "text_category": "",
                        "text_type": "",
                        "tags": []
                    }
                },
                {
                    "id": "5e347198176f49b8ab57ffb8463a247d",
                    "shape_attributes": {
                        "name": "rect",
                        "x": 908,
                        "y": 713,
                        "width": 963,
                        "height": 63
                    },
                    "region_attributes": {
                        "formal_key": "",
                        "key_type": "other",
                        "label": "\u7cbe\u67fb\u306e\u5fc5\u8981\u306f\u3042\u308a\u307e\u305b\u3093\u304c\u5f8c\u65e5\u6539\u3081\u3066\u691c\u67fb\u3092\u3057\u307e\u3057\u3087\u3046.",
                        "note": "",
                        "text_category": "",
                        "text_type": "",
                        "tags": []
                    }
                },
                {
                    "id": "9101a2754cc348dd9e547c942d16a3c5",
                    "shape_attributes": {
                        "name": "rect",
                        "x": 111,
                        "y": 695,
                        "width": 208,
                        "height": 45
                    },
                    "region_attributes": {
                        "formal_key": "",
                        "key_type": "other",
                        "label": "C3:\u8981\u518d\u691c\u67fb",
                        "note": "",
                        "text_category": "",
                        "text_type": "",
                        "tags": []
                    }
                },
                {
                    "id": "e2a39f43ceaf4ecb8ede31fa3084f8ca",
                    "shape_attributes": {
                        "name": "rect",
                        "x": 907,
                        "y": 647,
                        "width": 860,
                        "height": 58
                    },
                    "region_attributes": {
                        "formal_key": "",
                        "key_type": "other",
                        "label": "\u4eca\u306e\u751f\u6d3b\u3092\u898b\u76f4\u3057\u3066.\u3088\u308a\u5065\u5eb7\u7684\u306b\u904e\u3054\u3057\u307e\u3057\u3087\u3046.",
                        "note": "",
                        "text_category": "",
                        "text_type": "",
                        "tags": []
                    }
                },
                {
                    "id": "3c86d462ab9a4afaaacf038b6650d93d",
                    "shape_attributes": {
                        "name": "rect",
                        "x": 107,
                        "y": 624,
                        "width": 702,
                        "height": 70
                    },
                    "region_attributes": {
                        "formal_key": "",
                        "key_type": "other",
                        "label": "C1:\u8981\u7d4c\u904e\u89b3\u5bdfC2:\u8981\u751f\u6d3b\u6539\u5584C:\u8981\u6307\u5c0e",
                        "note": "",
                        "text_category": "",
                        "text_type": "",
                        "tags": []
                    }
                },
                {
                    "id": "ca37098cc3004f35b2ca374190be978b",
                    "shape_attributes": {
                        "name": "rect",
                        "x": 905,
                        "y": 580,
                        "width": 936,
                        "height": 49
                    },
                    "region_attributes": {
                        "formal_key": "",
                        "key_type": "other",
                        "label": "\u7279\u306b\u554f\u984c\u306f\u3042\u308a\u307e\u305b\u3093.\u6765\u5e74\u3082\u5065\u5eb7\u8a3a\u65ad\u3092\u53d7\u3051\u307e\u3057\u3087\u3046.",
                        "note": "",
                        "text_category": "",
                        "text_type": "",
                        "tags": []
                    }
                },
                {
                    "id": "eea79fedee634fe7858392a46c6ea76b",
                    "shape_attributes": {
                        "name": "rect",
                        "x": 107,
                        "y": 555,
                        "width": 484,
                        "height": 63
                    },
                    "region_attributes": {
                        "formal_key": "",
                        "key_type": "other",
                        "label": "A:\u7570\u5e38\u306a\u3057B:\u307b\u307c\u6b63\u5e38",
                        "note": "",
                        "text_category": "",
                        "text_type": "",
                        "tags": []
                    }
                },
                {
                    "id": "7aea55d3a97e4b0c93db2d16f2107090",
                    "shape_attributes": {
                        "name": "rect",
                        "x": 302,
                        "y": 457,
                        "width": 343,
                        "height": 64
                    },
                    "region_attributes": {
                        "formal_key": "",
                        "key_type": "other",
                        "label": "\u5065\u5eb7\u8a3a\u65ad\u306e\u5224\u5b9a",
                        "note": "",
                        "text_category": "",
                        "text_type": "",
                        "tags": []
                    }
                },
                {
                    "id": "435b9ef54c6543cc8b0fe81470f1e272",
                    "shape_attributes": {
                        "name": "rect",
                        "x": 95,
                        "y": 326,
                        "width": 929,
                        "height": 70
                    },
                    "region_attributes": {
                        "formal_key": "",
                        "key_type": "other",
                        "label": "\u304f\u5065\u5eb7\u8a3a\u65ad\u306e\u5224\u5b9a\u3068\u691c\u67fb\u9805\u76ee\u306e\u8aac\u660e\u226b",
                        "note": "",
                        "text_category": "",
                        "text_type": "",
                        "tags": []
                    }
                },
                {
                    "id": "cc0b47c2fab34636ad3dc4fa74fd1696",
                    "shape_attributes": {
                        "name": "rect",
                        "x": 86,
                        "y": 235,
                        "width": 419,
                        "height": 52
                    },
                    "region_attributes": {
                        "formal_key": "",
                        "key_type": "other",
                        "label": "\u5927\u5207\u306b\u4fdd\u7ba1\u3057\u3066\u304f\u3060\u3055\u3044",
                        "note": "",
                        "text_category": "",
                        "text_type": "",
                        "tags": []
                    }
                },
                {
                    "id": "0027ba65e14b4c38b3d47d4149b71b7a",
                    "shape_attributes": {
                        "name": "rect",
                        "x": 83,
                        "y": 173,
                        "width": 1797,
                        "height": 63
                    },
                    "region_attributes": {
                        "formal_key": "",
                        "key_type": "other",
                        "label": "\u5065\u5eb7\u8a3a\u65ad\u306e\u7d50\u679c\u3092,\u305c\u3072\u3054\u81ea\u8eab\u306e\u5065\u5eb7\u7ba1\u7406\u306b\u304a\u5f79\u7acb\u3066\u304f\u3060\u3055\u3044.\u307e\u305f\u3001\u5065\u5eb7\u8a3a\u65ad\u306e\u7d50\u679c\u306f\u518d\u767a\u884c\u3057\u3066\u304a\u308a\u307e\u305b\u3093,",
                        "note": "",
                        "text_category": "",
                        "text_type": "",
                        "tags": []
                    }
                },
                {
                    "id": "46cf413e3d924d0d8a39b9de2691bdad",
                    "shape_attributes": {
                        "name": "rect",
                        "x": 119,
                        "y": 109,
                        "width": 1498,
                        "height": 58
                    },
                    "region_attributes": {
                        "formal_key": "",
                        "key_type": "other",
                        "label": "\u3053\u306e\u5ea6\u306fJR\u672d\u5e4c\u75c5\u9662\u4fdd\u5065\u7ba1\u7406\u90e8\u3067.\u5065\u5eb7\u8a3a\u65ad\u3092\u53d7\u691c\u3057\u3066\u3044\u305f\u3060\u304d\u3042\u308a\u304c\u3068\u3046\u3054\u3056\u3044\u307e\u3057\u305f.",
                        "note": "",
                        "text_category": "",
                        "text_type": "",
                        "tags": []
                    }
                }
            ]
        },
        "_via_attributes": {
            "region": {
                "label": {
                    "type": "text",
                    "description": "",
                    "default_value": ""
                },
                "key_type": {
                    "type": "dropdown",
                    "description": "",
                    "options": {
                        "key": "",
                        "value": "",
                        "master_key": "",
                        "other": ""
                    },
                    "default_options": {
                        "other": "true"
                    }
                },
                "text_category": {
                    "type": "dropdown",
                    "description": "",
                    "options": {
                        "name": "",
                        "address": "",
                        "email": "",
                        "number": "",
                        "alphabet": "",
                        "japanese": "",
                        "checkbox": "",
                        "mix": ""
                    },
                    "default_options": {
                        "mix": "true"
                    }
                },
                "text_type": {
                    "type": "dropdown",
                    "description": "",
                    "options": {
                        "handwriting": "",
                        "printed": "",
                        "mixed": ""
                    },
                    "default_options": {
                        "printed": "true"
                    }
                },
                "formal_key": {
                    "type": "text",
                    "description": "",
                    "default_value": ""
                },
                "note": {
                    "type": "text",
                    "description": "",
                    "default_value": ""
                }
            },
            "file": {}
        }
    }
}